ml_engine/__init__.py
ml_engine/models/__init__.py
ml_engine/utils/__init__.py
ml_engine/utils/images.py
platform_ai-0.0.1.dist-info/METADATA
platform_ai-0.0.1.dist-info/RECORD
platform_ai-0.0.1.dist-info/WHEEL
platform_ai-0.0.1.dist-info/top_level.txt
