Metadata-Version: 2.1
Name: platform-ai
Version: 0.0.1
Summary: Prediction API client for Python
Home-page: https://github.com/pypa/sampleproject
Author: Arshak Navruzyan
Author-email: arshak@platform.ai
License: UNKNOWN
Platform: UNKNOWN
Classifier: Programming Language :: Python :: 3
Classifier: License :: OSI Approved :: MIT License
Classifier: Operating System :: OS Independent
